{
  "updated": "2026-06-23T21:19:58.312681+08:00",
  "source": "A股聚合",
  "count": 44,
  "items": [
    {
      "title": "RadexMarkets瑞德克斯:金银中期仍受利率牵制",
      "link": "https://finance.sina.com.cn/money/future/roll/2026-06-23/doc-iniemfsp8654046.shtml",
      "date": "2026-06-23 21:18",
      "summary": "6月23日，最新市场消息显示，贵金属板块近期虽有修复动作，但中期仍面临偏鹰利率环境带来的持续牵制。RadexMarkets瑞德克斯在梳理盘面变化时提到...",
      "source": "市场资讯",
      "category": "a-stock"
    },
    {
      "title": "伊朗强调可自由使用被解冻资产icon_voice_onicon_voice",
      "link": "https://finance.sina.com.cn/stock/marketresearch/2026-06-23/doc-iniemfsn1877113.shtml",
      "date": "2026-06-23 21:18",
      "summary": "新华社德黑兰6月23日电（记者沙达提 陈霄）据伊朗伊斯兰共和国通讯社23日报道，伊朗外交部发言人巴加埃当天在德黑兰举行的每周例行记者会上表示...",
      "source": "新华社",
      "category": "a-stock"
    },
    {
      "title": "FPG财盛国际:油气复苏仍受资本约束",
      "link": "https://finance.sina.com.cn/money/future/roll/2026-06-23/doc-iniemfsm6339608.shtml",
      "date": "2026-06-23 21:16",
      "summary": "6月23日，最新市场消息显示，多家国际能源企业重新关注委内瑞拉油气资产，带动当地增产预期重新升温。FPG财盛国际在梳理盘面变化时提到...",
      "source": "市场资讯",
      "category": "a-stock"
    },
    {
      "title": "CBCX:代币化进展慢于预期",
      "link": "https://finance.sina.com.cn/money/future/roll/2026-06-23/doc-iniemfsp8652060.shtml",
      "date": "2026-06-23 21:14",
      "summary": "6月23日，最新市场消息显示，围绕资产代币化的市场热度持续升温，但业内判断认为传统金融基础设施尚未完全准备好承接大规模落地。",
      "source": "市场资讯",
      "category": "a-stock"
    },
    {
      "title": "3200亿光纤巨头紧急风险提示，“924”行情以来暴涨24倍，年内涨幅跑赢超99%个股",
      "link": "https://finance.sina.com.cn/stock/s/2026-06-23/doc-iniemfsn1874911.shtml",
      "date": "2026-06-23 21:08",
      "summary": "6月23日晚间，长飞光纤（601869.SH）最新公告称，公司股票连续两个交易日收盘价格涨幅偏离值累计超过20%，属于股票交易异常波动。",
      "source": "21世纪经济报道",
      "category": "a-stock"
    },
    {
      "title": "农业银行新疆维吾尔自治区分行被罚30万元：员工行为管理不到位",
      "link": "https://finance.sina.com.cn/jryx/fd/2026-06-23/doc-iniemfsp8646119.shtml",
      "date": "2026-06-23 21:03",
      "summary": "6月23日金融一线消息，据新疆金融监管局行政处罚信息公示列表显示，中国农业银行股份有限公司新疆维吾尔自治区分行因员工行为管理不到位，被罚款30万元；相关责任人钟淼...",
      "source": "金融一线",
      "category": "a-stock"
    },
    {
      "title": "中天策略:6月23日市场分析",
      "link": "https://finance.sina.com.cn/money/future/fmnews/2026-06-23/doc-iniemfsp8645695.shtml",
      "date": "2026-06-23 21:01",
      "summary": "",
      "source": "市场资讯",
      "category": "a-stock"
    },
    {
      "title": "中国人民银行法修订草案首次提请审议",
      "link": "https://finance.sina.com.cn/money/bank/bank_yhfg/2026-06-23/doc-iniemfsi9554609.shtml",
      "date": "2026-06-23 20:55",
      "summary": "来源：中国金融 记者：刘宏振 2026年6月23日，《中华人民共和国中国人民银行法（修订草案）》提请十四届全国人大常委会第二十三次会议首次审议。",
      "source": "市场资讯",
      "category": "a-stock"
    },
    {
      "title": "中国人民银行法修订草案首次提请全国人大常委会会议审议",
      "link": "https://finance.sina.com.cn/wm/2026-06-23/doc-iniemfsp8645618.shtml",
      "date": "2026-06-23 20:53",
      "summary": "来源：金融时报 2026年6月23日，《中华人民共和国中国人民银行法（修订草案）》提请十四届全国人大常委会第二十三次会议首次审议。",
      "source": "市场资讯",
      "category": "a-stock"
    },
    {
      "title": "聚焦降低词元成本的AI记忆初创企业完成9800万美元融资",
      "link": "https://finance.sina.com.cn/stock/usstock/c/2026-06-23/doc-iniemfsi9552611.shtml",
      "date": "2026-06-23 20:52",
      "summary": "核心要点 AI 记忆初创企业 Engram（记忆印迹）完成近 1 亿美元融资，旨在提升模型运行效率、遏制暴涨的 AI 使用成本。 该公司称，旗下模型最高可节省 99% 的词元用量...",
      "source": "环球市场播报",
      "category": "a-stock"
    },
    {
      "title": "邦达亚洲:美元的避险买需降温 黄金小幅收涨",
      "link": "https://finance.sina.com.cn/money/forex/forexfxyc/2026-06-23/doc-iniemfsp8642316.shtml",
      "date": "2026-06-23 20:52",
      "summary": "6月23日，受美国经济展现出的韧性以及美联储新任主席凯文·沃什采取更为鹰派的立场影响，美国银行全球研究部和德意志银行现在均预计，美联储今年将上调利率。",
      "source": "市场资讯",
      "category": "a-stock"
    },
    {
      "title": "中国拟修订中国人民银行法 加快完善中央银行制度",
      "link": "https://finance.sina.com.cn/roll/2026-06-23/doc-iniemfsi9553192.shtml",
      "date": "2026-06-23 20:52",
      "summary": "中新社北京6月23日电 （记者 谢雁冰 曾玥）中国人民银行法修订草案23日提请十四届全国人大常委会第二十三次会议初次审议，加快完善中央银行制度。",
      "source": "中国新闻网",
      "category": "a-stock"
    },
    {
      "title": "多只医药主题基金周二逆势领涨，资源主题基金领跌",
      "link": "https://finance.sina.com.cn/roll/2026-06-23/doc-iniemfsp8643060.shtml",
      "date": "2026-06-23 20:52",
      "summary": "记者|肖芮冬 编辑|赵云 6月23日，市场震荡调整，创业板指、深成指低开低走。板块来看，医药板块逆势走强，人形机器人概念表现活跃，磷化工板块延续强势...",
      "source": "每日经济新闻",
      "category": "a-stock"
    },
    {
      "title": "上海高金学院朱宁：AI是人类历史上最伟大发明，没有之一",
      "link": "https://finance.sina.com.cn/hy/hyjz/2026-06-23/doc-iniemfsp8641800.shtml",
      "date": "2026-06-23 20:52",
      "summary": "6月23日，“2026夏季达沃斯新浪财经之夜”在大连重磅举行，主题为“AI时代的可持续创新与规模化路径”。上海高级金融学院副院长，金融学讲席教授朱宁出席并演讲。",
      "source": "睿见Economy",
      "category": "a-stock"
    },
    {
      "title": "栽了！“纵容”老员工违规，国泰海通被监管点名",
      "link": "https://finance.sina.com.cn/stock/quanshang/qsyj/2026-06-23/doc-iniemfsp8641137.shtml",
      "date": "2026-06-23 20:45",
      "summary": "时隔月余，行家的猜测得以实锤：继对“失联”的时任国泰君安经纪人公告送达拟“禁业”处罚后，涉事的营业部，因“未采取有效措施规范从业人员执业行为”，也被监管追责。",
      "source": "市场资讯",
      "category": "a-stock"
    },
    {
      "title": "人工智能时代，谷歌的线上霸主地位显露松动迹象",
      "link": "https://finance.sina.com.cn/stock/usstock/c/2026-06-23/doc-iniekzkm9678172.shtml",
      "date": "2026-06-23 20:44",
      "summary": "核心要点 尽管在华尔街眼中谷歌依旧实力雄厚，但人工智能时代让这家企业的发展前景变得错综复杂，也暴露出诸多隐忧。 谷歌一方面面临各类人工智能模型与服务带来的激烈竞争...",
      "source": "环球市场播报",
      "category": "a-stock"
    },
    {
      "title": "中国人民银行法拟修改 健全宏观审慎制度框架",
      "link": "https://finance.sina.com.cn/money/bank/bank_yhfg/2026-06-23/doc-iniemfsp8639629.shtml",
      "date": "2026-06-23 20:43",
      "summary": "原标题：人大常委会|中国人民银行法拟修改 健全宏观审慎制度框架 新华社北京6月23日电（记者吴雨）中国人民银行法修订草案6月23日提请全国人大常委会会议初次审议。",
      "source": "新华社",
      "category": "a-stock"
    },
    {
      "title": "欧盟据称将升级对Meta的调查 指控其产品导致儿童上瘾",
      "link": "https://finance.sina.com.cn/stock/usstock/c/2026-06-23/doc-iniekzkr8767406.shtml",
      "date": "2026-06-23 20:43",
      "summary": "欧盟准备加大对Meta Platforms Inc．的调查力度，指控其产品导致儿童上瘾。这标志着欧盟对这家美国社交媒体巨头的监管压力进一步升级。",
      "source": "环球市场播报",
      "category": "a-stock"
    },
    {
      "title": "中国太平总经理李可东：保险资金有利于破解长周期项目资金供需错配难题",
      "link": "https://finance.sina.com.cn/money/insurance/bxyx/2026-06-23/doc-iniekzkq1989483.shtml",
      "date": "2026-06-23 20:41",
      "summary": "来源：金融时报 “气候风险已从过去‘低频率、高损失’的偶发事件，演变为系统性、全球化、常态化的风险形态，而保险在这一过程中的风险缓释作用仍有待充分释放。",
      "source": "市场资讯",
      "category": "a-stock"
    },
    {
      "title": "ADP：截至6月6日的四周 美国私营部门就业人数平均每周增加30750人",
      "link": "https://finance.sina.com.cn/stock/usstock/c/2026-06-23/doc-iniekzkq1988697.shtml",
      "date": "2026-06-23 20:41",
      "summary": "根据ADP Research和斯坦福数字经济实验室的初步估计，截至6月6日的四周内，美国私营部门就业人数平均每周增加30，750人。",
      "source": "环球市场播报",
      "category": "a-stock"
    },
    {
      "title": "美国6月费城联储非制造业指数降至-25.8",
      "link": "https://finance.sina.com.cn/stock/usstock/c/2026-06-23/doc-iniekzkm9676055.shtml",
      "date": "2026-06-23 20:40",
      "summary": "据费城联储数据显示，地区整体商业活动指数从上月的-23.6降至-25.8。 6月份企业总体活动指数升至2.4，而前值为-3.8。 新订单指数升至-0.7，而前值为-0.8。",
      "source": "环球市场播报",
      "category": "a-stock"
    },
    {
      "title": "蒋锡培：每个人赚钱不容易，用好财富非常重要",
      "link": "https://finance.sina.com.cn/hy/hyjz/2026-06-23/doc-iniekzkp6452351.shtml",
      "date": "2026-06-23 20:38",
      "summary": "6月23日，“2026夏季达沃斯新浪财经之夜”在大连重磅举行，本次活动主题为“AI时代的可持续创新与规模化路径”。远东控股集团创始人、董事局主席蒋锡培在演讲中谈到...",
      "source": "睿见Economy",
      "category": "a-stock"
    },
    {
      "title": "蒋锡培：拥抱年轻人，all in AI",
      "link": "https://finance.sina.com.cn/hy/hyjz/2026-06-23/doc-iniekzkq1987400.shtml",
      "date": "2026-06-23 20:38",
      "summary": "6月23日，“2026夏季达沃斯新浪财经之夜”在大连重磅举行，本次活动主题为“AI时代的可持续创新与规模化路径”。远东控股集团创始人、董事局主席蒋锡培在演讲中谈到...",
      "source": "睿见Economy",
      "category": "a-stock"
    },
    {
      "title": "两位参议员就关税对制造业的影响向特朗普政府施压",
      "link": "https://finance.sina.com.cn/stock/usstock/c/2026-06-23/doc-iniekzkr8764483.shtml",
      "date": "2026-06-23 20:37",
      "summary": "核心要点 马萨诸塞州民主党联邦参议员伊丽莎白・沃伦、亚利桑那州民主党联邦参议员马克・凯利向特朗普政府三位内阁官员致信（该信件由美国消费者新闻与商业频道...",
      "source": "环球市场播报",
      "category": "a-stock"
    },
    {
      "title": "邦达亚洲:经济数据表现疲软 欧元小幅收跌",
      "link": "https://finance.sina.com.cn/money/forex/forexfxyc/2026-06-23/doc-iniekzkq1986869.shtml",
      "date": "2026-06-23 20:37",
      "summary": "6月23日，欧洲央行行长拉加德在欧洲议会听证会上表示，欧元区当前面临的通胀冲击规模不容忽视，但尚未对长期通胀预期造成扰动，也未形成需要更激进政策应对的“二轮效应”。...",
      "source": "市场资讯",
      "category": "a-stock"
    },
    {
      "title": "筹划控制权变更，ST星农明起停牌！",
      "link": "https://finance.sina.com.cn/stock/s/2026-06-23/doc-iniekzkm9674941.shtml",
      "date": "2026-06-23 20:34",
      "summary": "来源：证券日报之声 本报记者 吴奕萱 见习记者 戚辰琪 6月23日晚间，星光农机股份有限公司（以下简称“ST星农”）发布了关于筹划控制权变更事项的停牌公告。",
      "source": "市场资讯",
      "category": "a-stock"
    },
    {
      "title": "全国首例！金融“反内卷”走向制度化，吉林按季报送、定期通报",
      "link": "https://finance.sina.com.cn/roll/2026-06-23/doc-iniemfsi9555131.shtml",
      "date": "2026-06-23 20:33",
      "summary": "21世纪经济报道记者 边万莉 金融反内卷，已有地方迈出了制度化的一步。 近日，国家金融监督管理总局吉林监管局宣布，建立无序竞争监测通报机制。",
      "source": "21世纪经济报道",
      "category": "a-stock"
    },
    {
      "title": "阿曼与伊朗联合声明 将保障霍尔木兹海峡安全通行",
      "link": "https://finance.sina.com.cn/stock/marketresearch/2026-06-23/doc-iniekzkq1986752.shtml",
      "date": "2026-06-23 20:30",
      "summary": "新华社多哈6月23日电（记者汪强）马斯喀特消息：阿曼与伊朗23日在马斯喀特发表联合声明说，作为霍尔木兹海峡沿岸国家，阿曼和伊朗重申，双方将根据适用的国际法...",
      "source": "新华社",
      "category": "a-stock"
    },
    {
      "title": "盘前：纳指期货跌2.59% 全球科技股疯狂暴跌",
      "link": "https://finance.sina.com.cn/stock/usstock/c/2026-06-23/doc-iniekzkp6447476.shtml",
      "date": "2026-06-23 20:30",
      "summary": "周二，全球市场出现连锁抛售，投资者对高涨的科技股和泡沫化估值感到不安。韩国Kospi指数暴跌10%，纳斯达克指数期货下跌逾2%，全球科技股抛售加速。",
      "source": "环球市场播报",
      "category": "a-stock"
    },
    {
      "title": "王毅谈美伊冲突的启示",
      "link": "https://finance.sina.com.cn/stock/marketresearch/2026-06-23/doc-iniekzkm9672841.shtml",
      "date": "2026-06-23 20:30",
      "summary": "新华社新德里6月23日电（记者陈冬书 伍岳）6月23日，中共中央政治局委员、中央外办主任王毅在新德里出席金砖国家安全事务高级代表会议时表示...",
      "source": "新华社",
      "category": "a-stock"
    },
    {
      "title": "海天味业的两百亿难题",
      "link": "https://finance.sina.com.cn/stock/s/2026-06-23/doc-iniekzkm9678866.shtml",
      "date": "2026-06-23 20:29",
      "summary": "2026年6月23日，海天味业（603288）公告了一份10亿到20亿元的股份回购预案，回购价格上限53元/股，其中70%以上将用于注销减少注册资本。",
      "source": "红星资本局",
      "category": "a-stock"
    },
    {
      "title": "5076亿网商银行股权“暗战”：史玉柱、鲁伟鼎退，仇建平进",
      "link": "https://finance.sina.com.cn/stock/roll/2026-06-23/doc-iniekzkr8766279.shtml",
      "date": "2026-06-23 20:20",
      "summary": "作者 |刘银平 编辑 | 付影 来源 | 独角金融 民营银行“头雁”网商银行，正迎来一次股东阵营的换防。 6月21日晚，手工具龙头巨星科技（002444.SZ）发布公告称，拟以3...",
      "source": "市场资讯",
      "category": "a-stock"
    },
    {
      "title": "603789，股价涨停！筹划控制权变更，明起停牌！",
      "link": "https://finance.sina.com.cn/stock/s/2026-06-23/doc-iniekzkm9672026.shtml",
      "date": "2026-06-23 20:07",
      "summary": "6月23日，ST星农（603789）呈现涨停走势。截至全天收盘，ST星农收于5.49元，上涨0.26元，涨幅为4.97%。 ST星农6月23日晚公告，公司于2026年6月23日收到公司股东湖州新家园...",
      "source": "新浪财经2",
      "category": "a-stock"
    },
    {
      "title": "2025的Flag，李蓓实现了多少？",
      "link": "https://finance.sina.com.cn/stock/marketresearch/2026-06-23/doc-iniemfsm6340055.shtml",
      "date": "2026-06-23 20:03",
      "summary": "来源：财闻 2025年李蓓曾立下诸多旗帜鲜明的判断。站在2026年6月回头看，市场走出了一条更曲折的路径。 6月21日，半夏投资创始人李蓓的一封致投资人信在圈内传开。",
      "source": "市场资讯",
      "category": "a-stock"
    },
    {
      "title": "股价“抢跑”！ST星农停牌，筹划易主！",
      "link": "https://finance.sina.com.cn/stock/s/2026-06-23/doc-iniekzkp6452444.shtml",
      "date": "2026-06-23 20:01",
      "summary": "来源：资本秘闻 6月23日涨停收盘的ST星农，于当日晚间披露公告称，因筹划控制权变更事项，公司股票将于6月24日起停牌，预计停牌时间不超过2个交易日。",
      "source": "市场资讯",
      "category": "a-stock"
    },
    {
      "title": "宁泉资产，持仓曝光",
      "link": "https://finance.sina.com.cn/stock/marketresearch/2026-06-23/doc-iniekzkq1983427.shtml",
      "date": "2026-06-23 20:01",
      "summary": "知名私募大佬杨东执掌的宁泉资产，近日发布了《给持有人的一封信：2026年半年投资汇报》。 宁泉资产在信中坦言，今年公司业绩没有做好，要向持有人说一声抱歉。",
      "source": "上海证券报",
      "category": "a-stock"
    },
    {
      "title": "运动休闲品牌Vuori开启全球零售扩张，将中国作为核心布局市场",
      "link": "https://finance.sina.com.cn/stock/usstock/c/2026-06-23/doc-iniekzkq1968696.shtml",
      "date": "2026-06-23 20:00",
      "summary": "这家露露乐蒙（Lululemon）、Alo 的竞品品牌计划到 2030 年末，将海内外门店数量扩充一倍2024 年，在泛大西洋投资集团与 Stripes 基金主导的二级要约收购中...",
      "source": "环球市场播报",
      "category": "a-stock"
    },
    {
      "title": "存储芯片，全线跳水！闪迪、美光科技盘前一度跌超10%",
      "link": "https://finance.sina.com.cn/wm/2026-06-23/doc-iniekzkq1974179.shtml",
      "date": "2026-06-23 19:58",
      "summary": "（来源：中国基金报） 【导读】美股存储芯片盘前全线重挫，费城半导体指数30只成份股集体大跌 中国基金报记者 张舟 北京时间6月23日，美股存储芯片盘前全线重挫...",
      "source": "滚动播报",
      "category": "a-stock"
    },
    {
      "title": "欧洲央行首席经济学家：通胀率可能较长时间维持在2%以上",
      "link": "https://finance.sina.com.cn/world/2026-06-23/doc-iniekzkr8744205.shtml",
      "date": "2026-06-23 19:55",
      "summary": "欧洲央行首席经济学家Philip Lane称，该央行的官员正面临这样的风险：通货膨胀率将“在相当长一段时间内”徘徊在目标水平之上。",
      "source": "环球市场播报",
      "category": "a-stock"
    },
    {
      "title": "欧洲多地遭遇极端高温：英、法、西、意发布高温红色预警",
      "link": "https://finance.sina.com.cn/stock/usstock/c/2026-06-23/doc-iniekzkm9653379.shtml",
      "date": "2026-06-23 19:55",
      "summary": "核心要点欧洲多国发布气象红色预警，极端高温天气下气温突破 40 摄氏度（104 华氏度）。英国气象局表示，未来几天英国极有可能刷新 6 月历史最高气温纪录。",
      "source": "环球市场播报",
      "category": "a-stock"
    },
    {
      "title": "欧洲央行管委Escrivá：油价高企开始影响到经济的其他领域",
      "link": "https://finance.sina.com.cn/world/2026-06-23/doc-iniekzkm9653258.shtml",
      "date": "2026-06-23 19:55",
      "summary": "欧洲央行管委会成员Jose Luis Escrivá表示，高油价正在对经济的其他领域产生影响。 “除了所有经济体的能源价格上涨，特别是油价上涨之外，间接影响也日益明显...",
      "source": "环球市场播报",
      "category": "a-stock"
    },
    {
      "title": "巴克莱据悉考虑重返日本现金股票业务",
      "link": "https://finance.sina.com.cn/world/2026-06-23/doc-iniekzkr8743707.shtml",
      "date": "2026-06-23 19:54",
      "summary": "知情人士称，巴克莱考虑在退出日本现金股票业务十年后重返该业务领域。 知情人士透露，相关讨论尚处于早期阶段，尚未做出任何决定。巴克莱近来一直在东京招聘股票专家。",
      "source": "环球市场播报",
      "category": "a-stock"
    },
    {
      "title": "德国总理默茨：将推进提高退休年龄的计划",
      "link": "https://finance.sina.com.cn/world/2026-06-23/doc-iniekzkr8743409.shtml",
      "date": "2026-06-23 19:53",
      "summary": "德国总理弗里德里希·默茨表示，政府将推进一个委员会提交、旨在改善德国公共养老金体系资金状况的所有建议。 这些33项建议措施包括建立市场化基金...",
      "source": "环球市场播报",
      "category": "a-stock"
    },
    {
      "title": "伊朗称并未计划允许国际原子能机构检查受损核设施",
      "link": "https://finance.sina.com.cn/world/2026-06-23/doc-iniekzkq1965914.shtml",
      "date": "2026-06-23 19:53",
      "summary": "伊朗外交部发言人Esmail Baghaei在每周例行新闻发布会上表示，伊朗并未计划让国际原子能机构检查在美国和以色列军事袭击中受损的核设施，且目前尚无此类检查的相关规程。",
      "source": "环球市场播报",
      "category": "a-stock"
    }
  ]
}