{
  "updated": "2026-07-21T06:56:55.906809+08:00",
  "source": "A股聚合",
  "count": 35,
  "items": [
    {
      "title": "现实版“是，首相”再度上演：伯纳姆新内阁群英谱",
      "link": "https://finance.sina.com.cn/world/2026-07-21/doc-iniiphzq8091807.shtml",
      "date": "2026-07-21 06:56",
      "summary": "安迪·伯纳姆在唐宁街10号著名的黑色大门前发表了他就任英国首相后的首次演讲，誓言要为该国带来“近40年来最大的变革”。他的内阁首当其冲。",
      "source": "环球市场播报",
      "category": "a-stock"
    },
    {
      "title": "新浪财经CEO邓庆旭：经过20多年，我们发现一条企业成长规律",
      "link": "https://finance.sina.com.cn/hy/hyjz/2026-07-21/doc-iniiphzq8071214.shtml",
      "date": "2026-07-21 06:32",
      "summary": "美国当地时间7月20日，新浪财经联合美国中国总商会举办的“超越赛场——中美商业、人工智能与全球协作”私享会在纽约举行。",
      "source": "睿见Economy",
      "category": "a-stock"
    },
    {
      "title": "新浪财经CEO邓庆旭：连接，比对抗更有力量",
      "link": "https://finance.sina.com.cn/hy/hyjz/2026-07-21/doc-iniiphzm2601911.shtml",
      "date": "2026-07-21 06:31",
      "summary": "美国当地时间7月20日，新浪财经联合美国中国总商会举办的“超越赛场——中美商业、人工智能与全球协作”私享会在纽约举行。",
      "source": "睿见Economy",
      "category": "a-stock"
    },
    {
      "title": "新浪财经CEO邓庆旭：这是一届“AI不吹哨、但无处不在”的世界杯",
      "link": "https://finance.sina.com.cn/hy/hyjz/2026-07-21/doc-iniiphzq8069358.shtml",
      "date": "2026-07-21 06:30",
      "summary": "美国当地时间7月20日，新浪财经联合美国中国总商会举办的“超越赛场——中美商业、人工智能与全球协作”私享会在纽约举行。",
      "source": "睿见Economy",
      "category": "a-stock"
    },
    {
      "title": "7月21日隔夜要闻：美股收跌 油价上涨 派拉蒙收购华纳兄弟被叫停 英国新任首相任命多名内阁成员 英债下跌",
      "link": "https://finance.sina.com.cn/stock/usstock/c/2026-07-21/doc-iniipatu4970076.shtml",
      "date": "2026-07-21 06:30",
      "summary": "市场 7月21日收盘：油价上涨拖累美股收跌 道指下跌逾300点 7月21日美股成交额前20：苹果涨价动摇核心用户升级意愿 7月21日热门中概股多数上涨 阿里巴巴涨4.69%...",
      "source": "环球市场播报",
      "category": "a-stock"
    },
    {
      "title": "新浪财经CEO邓庆旭：中国企业成世界杯“技术合伙人”，远超场边广告牌价值",
      "link": "https://finance.sina.com.cn/hy/hyjz/2026-07-21/doc-iniiphzs4844778.shtml",
      "date": "2026-07-21 06:28",
      "summary": "美国当地时间7月20日，新浪财经联合美国中国总商会举办的“超越赛场——中美商业、人工智能与全球协作”私享会在纽约举行。",
      "source": "睿见Economy",
      "category": "a-stock"
    },
    {
      "title": "新浪财经CEO邓庆旭：世界杯是全球技术进步“压力测试场”，中国企业成技术底座",
      "link": "https://finance.sina.com.cn/hy/hyjz/2026-07-21/doc-iniiphzm2600052.shtml",
      "date": "2026-07-21 06:27",
      "summary": "美国当地时间7月20日，新浪财经联合美国中国总商会举办的“超越赛场——中美商业、人工智能与全球协作”私享会在纽约举行。",
      "source": "睿见Economy",
      "category": "a-stock"
    },
    {
      "title": "美国股市：苹果和特斯拉下跌拖累大盘 芯片股反弹迎接财报大考",
      "link": "https://finance.sina.com.cn/stock/usstock/c/2026-07-21/doc-iniipatp2718061.shtml",
      "date": "2026-07-21 06:01",
      "summary": "标普500指数回吐早盘涨幅并收跌，苹果和特斯拉股价下跌抵消了其他涨势。芯片股在一系列财报公布前反弹，市场将检验大型科技公司的盈利能否达到市场的高预期。",
      "source": "环球市场播报",
      "category": "a-stock"
    },
    {
      "title": "沙特阿拉伯称将采取措施保护本国船只",
      "link": "https://finance.sina.com.cn/stock/usstock/c/2026-07-21/doc-iniipatp2717732.shtml",
      "date": "2026-07-21 06:00",
      "summary": "沙特阿拉伯外交部在社交媒体平台上发帖称，将根据国际法和1982年《联合国海洋法公约》采取一切必要措施保护本国船只。 沙特呼吁国际社会执行联合国安理会第2722号决议。",
      "source": "环球市场播报",
      "category": "a-stock"
    },
    {
      "title": "大宗商品综述：油价小幅上涨 金价企稳 伦铜走高",
      "link": "https://finance.sina.com.cn/stock/usstock/c/2026-07-21/doc-iniipatp2717419.shtml",
      "date": "2026-07-21 06:00",
      "summary": "受中东冲突升级的影响，油价周一在动荡的交易中小幅上涨，不过投资者也在关注调解方推动暂时停火的努力。黄金价格企稳，在伊朗紧张局势的背景下...",
      "source": "环球市场播报",
      "category": "a-stock"
    },
    {
      "title": "美国将对部分加拿大商品征收50%关税 首次援引从未启用法律条款",
      "link": "https://finance.sina.com.cn/stock/usstock/c/2026-07-21/doc-iniipatu4934746.shtml",
      "date": "2026-07-21 05:46",
      "summary": "特朗普政府将依据一项从未启用过的法律条款，对部分加拿大商品征收新的50%关税，理由是加拿大对美国酒类、汽车和乳制品采取了不公平待遇。",
      "source": "环球市场播报",
      "category": "a-stock"
    },
    {
      "title": "7月21日外盘头条：特朗普要让伊朗为美军身亡士兵付出代价 派拉蒙收购华纳交易被叫停",
      "link": "https://finance.sina.com.cn/stock/usstock/c/2026-07-21/doc-iniipatp2700533.shtml",
      "date": "2026-07-21 05:30",
      "summary": "全球财经媒体昨夜今晨共同关注的头条新闻主要有： 1、特朗普誓言要让伊朗为美军士兵身亡“付出代价” 调解方力促冲突降温 2、特朗普政府出新招：到美国建厂铝关税打对折 3...",
      "source": "环球市场播报",
      "category": "a-stock"
    },
    {
      "title": "美国宣布对加拿大部分产品加征50%关税",
      "link": "https://finance.sina.com.cn/jjxw/2026-07-21/doc-iniipats8162699.shtml",
      "date": "2026-07-21 05:02",
      "summary": "当地时间7月20日，白宫发布公告称，美国将对加拿大部分产品额外加征50%的从价关税，以应对“加拿大在汽车及汽车零部件贸易方面对美国采取的歧视性措施”。",
      "source": "央视",
      "category": "a-stock"
    },
    {
      "title": "沙特主导联军：正采取必要军事行动确保曼德海峡航运安全",
      "link": "https://finance.sina.com.cn/jjxw/2026-07-21/doc-iniipatq9490114.shtml",
      "date": "2026-07-21 04:56",
      "summary": "当地时间7月20日，沙特阿拉伯主导的多国联军指挥部发表声明称，联军已开始采取措施保护联盟国家船只通过曼德海峡，并将依据国际法和《联合国海洋法公约》...",
      "source": "央视",
      "category": "a-stock"
    },
    {
      "title": "原油：中东紧张局势推动油价小幅上涨",
      "link": "https://finance.sina.com.cn/stock/usstock/c/2026-07-21/doc-iniipatq9454307.shtml",
      "date": "2026-07-21 04:52",
      "summary": "油价周一在动荡的交易中小幅上涨，交易员一方面消化一连串显示中东冲突正在恶化的消息，另一方面也在评估推动战争暂时停火的努力。",
      "source": "环球市场播报",
      "category": "a-stock"
    },
    {
      "title": "7月21日美股成交额前20：苹果涨价动摇核心用户升级意愿",
      "link": "https://finance.sina.com.cn/stock/usstock/c/2026-07-21/doc-iniipatq9453604.shtml",
      "date": "2026-07-21 04:48",
      "summary": "周一美股成交额第1名美光科技收高1.94%，成交369.63亿美元。分析师指出，存储芯片行业供需博弈加剧，扩产与AI需求拉锯引发周期担忧。",
      "source": "环球市场播报",
      "category": "a-stock"
    },
    {
      "title": "美国中央司令部：美军对伊朗发动新一轮打击",
      "link": "https://finance.sina.com.cn/stock/usstock/c/2026-07-21/doc-iniipatp2672967.shtml",
      "date": "2026-07-21 04:28",
      "summary": "美国中央司令部发文称，美军于美东时间周一下午4时开始对伊朗发动新一轮打击，以进一步削弱伊朗袭击霍尔木兹海峡船只的能力。",
      "source": "环球市场播报",
      "category": "a-stock"
    },
    {
      "title": "特朗普政府出新招：到美国建厂铝关税打对折",
      "link": "https://finance.sina.com.cn/stock/usstock/c/2026-07-21/doc-iniipatu4866628.shtml",
      "date": "2026-07-21 04:26",
      "summary": "特朗普政府宣布激励措施，在美国新建、扩建或翻新铝厂的企业从国外进口该金属可享受关税折扣。 根据这项周一公布的方案，对于符合新要求并获得美国批准的公司...",
      "source": "环球市场播报",
      "category": "a-stock"
    },
    {
      "title": "7月21日热门中概股多数上涨 阿里巴巴涨4.69%，南茂科技跌8.33%",
      "link": "https://finance.sina.com.cn/stock/usstock/c/2026-07-21/doc-iniipatq9449196.shtml",
      "date": "2026-07-21 04:24",
      "summary": "7月21日热门中概股多数上涨，纳斯达克中国金龙指数（HXC）收高0.9%。 上涨个股（按市值从高到低）：台积电涨0.99%，阿里巴巴涨4.69%，拼多多涨2.27%，网易涨2.22%...",
      "source": "环球市场播报",
      "category": "a-stock"
    },
    {
      "title": "美军称对伊朗发动新一轮打击",
      "link": "https://finance.sina.com.cn/jjxw/2026-07-21/doc-iniipatp2673184.shtml",
      "date": "2026-07-21 04:18",
      "summary": "当地时间7月20日，美军中央司令部表示，美东时间当天下午4时，美军按照总统指示开始对伊朗发动新一轮打击。 美军中央司令部称，此次行动旨在进一步削弱伊朗威胁霍尔木兹海...",
      "source": "央视",
      "category": "a-stock"
    },
    {
      "title": "美官员：本月伊朗袭击已致近100名美军人员受伤",
      "link": "https://finance.sina.com.cn/jjxw/2026-07-21/doc-iniipats8090142.shtml",
      "date": "2026-07-21 04:16",
      "summary": "央视记者当地时间20日获悉，美国官员表示，本月伊朗针对中东地区美军基地发动的多次空袭已造成近100名美军人员受伤。 美国国防部首席发言人肖恩·帕内尔证实...",
      "source": "央视",
      "category": "a-stock"
    },
    {
      "title": "7月21日收盘：油价上涨拖累美股收跌 道指下跌逾300点",
      "link": "https://finance.sina.com.cn/stock/usstock/c/2026-07-21/doc-iniipatu4864105.shtml",
      "date": "2026-07-21 04:16",
      "summary": "北京时间7月21日凌晨，美股周一收跌。道指下跌逾300点。标普500指数下跌0.19%。市场继续关注美伊局势。特朗普称伊朗将为美国军人的死亡付出代价后，国际油价走高。",
      "source": "环球市场播报",
      "category": "a-stock"
    },
    {
      "title": "纽约汇市：美元震荡后企稳 加元与英镑下跌",
      "link": "https://finance.sina.com.cn/stock/usstock/c/2026-07-21/doc-iniipats8087110.shtml",
      "date": "2026-07-21 04:12",
      "summary": "一度因交易员密切关注美伊战争进展而出现震荡的彭博美元指数尾盘变化不大；数据显示加拿大CPI放缓后，加元兑美元下跌。",
      "source": "环球市场播报",
      "category": "a-stock"
    },
    {
      "title": "特朗普称伊朗将为杀害美国军人付出代价，油价周一上涨",
      "link": "https://finance.sina.com.cn/stock/usstock/c/2026-07-21/doc-iniipatu4863043.shtml",
      "date": "2026-07-21 04:11",
      "summary": "油价周一上涨，此前美国总统唐纳德·特朗普表示伊朗将为三名美国军人的死亡付出代价，且也门胡塞武装宣布对沙特阿拉伯实施海上禁运。",
      "source": "环球市场播报",
      "category": "a-stock"
    },
    {
      "title": "美国债市：国债追随英债下跌 也受到特朗普对伊朗威胁的拖累",
      "link": "https://finance.sina.com.cn/stock/usstock/c/2026-07-21/doc-iniipatp2669503.shtml",
      "date": "2026-07-21 04:07",
      "summary": "美国国债周一下跌，追随了英国国债跌势，此前英国新任首相安迪·伯纳姆表示将对英国财政规则中的灵活空间加以利用。此外，美国总统特朗普誓言要让伊朗为美军伤亡付出代价。...",
      "source": "环球市场播报",
      "category": "a-stock"
    },
    {
      "title": "投行BGL宣布将Strategic Thermal Labs出售给Vertiv",
      "link": "https://finance.sina.com.cn/stock/usstock/c/2026-07-21/doc-iniinwmw4990437.shtml",
      "date": "2026-07-21 03:59",
      "summary": "投资银行Brown Gibbons Lang &amp; Company周一宣布，将Strategic Thermal Labs（STL）出售给Vertiv Holdings Co．的全资子公司。",
      "source": "环球市场播报",
      "category": "a-stock"
    },
    {
      "title": "华纳音乐集团将于8月6日召开财报电话会议",
      "link": "https://finance.sina.com.cn/stock/usstock/c/2026-07-21/doc-iniinwmw4989059.shtml",
      "date": "2026-07-21 03:54",
      "summary": "华纳音乐集团周一宣布，将于2026年8月6日（周四）美国东部时间上午8：30举行电话会议，讨论其截至2026年6月30日的第三财季财务业绩。",
      "source": "环球市场播报",
      "category": "a-stock"
    },
    {
      "title": "AMD获微软扩大AI合作，Azure将部署Helios系统",
      "link": "https://finance.sina.com.cn/stock/usstock/c/2026-07-21/doc-iniinwmu8212552.shtml",
      "date": "2026-07-21 03:52",
      "summary": "超微半导体（AMD）周一宣布与微软大幅扩大战略合作，微软Azure云平台将部署AMD的Helios机架级AI系统，用于前沿模型推理及Azure AI服务。",
      "source": "环球市场播报",
      "category": "a-stock"
    },
    {
      "title": "Archer与Anduril联合发布“雷霆”自主攻击旋翼机",
      "link": "https://finance.sina.com.cn/stock/usstock/c/2026-07-21/doc-iniinwmr2797659.shtml",
      "date": "2026-07-21 03:48",
      "summary": "在2026年范堡罗国际航展首日，Anduril Industries与Archer Aviation联合发布了名为“雷霆”的自主攻击旋翼机。该机型被定位为第5组自主攻击旋翼机...",
      "source": "环球市场播报",
      "category": "a-stock"
    },
    {
      "title": "CMS Energy宣布季度股息，每股57美分",
      "link": "https://finance.sina.com.cn/stock/usstock/c/2026-07-21/doc-iniinwmu8211074.shtml",
      "date": "2026-07-21 03:47",
      "summary": "CMS Energy Corporation周一宣布，其董事会已批准向普通股股东派发季度股息，每股57美分。该股息将于2026年9月1日支付给2026年8月7日收盘时登记在册的股东。",
      "source": "环球市场播报",
      "category": "a-stock"
    },
    {
      "title": "也门宣布恢复石油出口",
      "link": "https://finance.sina.com.cn/jjxw/2026-07-21/doc-iniipatu4865892.shtml",
      "date": "2026-07-21 03:42",
      "summary": "当地时间7月20日，也门总统领导委员会主席拉沙德·穆罕默德·阿里米宣布，也门将自当天起恢复石油出口，并将石油收入用于发放工资、改善公共服务、促进经济稳定...",
      "source": "央视",
      "category": "a-stock"
    },
    {
      "title": "Old Republic携手Hope For The Warriors，宣布全国性合作伙伴关系",
      "link": "https://finance.sina.com.cn/stock/usstock/c/2026-07-21/doc-iniinwmr2796755.shtml",
      "date": "2026-07-21 03:42",
      "summary": "专业保险公司Old Republic International Corporation周一宣布，与致力于支持退伍军人、现役军人、军属及照护者的非营利组织Hope For The...",
      "source": "环球市场播报",
      "category": "a-stock"
    },
    {
      "title": "世界顶尖癌症中心Sheba采用Entolimod临床试验",
      "link": "https://finance.sina.com.cn/stock/usstock/c/2026-07-21/doc-iniinwmr2796449.shtml",
      "date": "2026-07-21 03:40",
      "summary": "位列《新闻周刊》2026年全球最佳医院第七位的以色列Sheba医疗中心，已正式确定临床试验方案，将评估Valion Bio公司药物Entolimod在癌症患者中的效果。",
      "source": "环球市场播报",
      "category": "a-stock"
    },
    {
      "title": "迪克体育加码投资女子体育，推出WNBA纪录片《Life In the W》",
      "link": "https://finance.sina.com.cn/stock/usstock/c/2026-07-21/doc-iniinwmu8209029.shtml",
      "date": "2026-07-21 03:38",
      "summary": "迪克体育用品公司周一宣布，其旗下内容制作工作室Cookie Jar &amp; A Dream Studios与ESPN合作推出的六集WNBA纪录片《Life In the W》将于7月24日首播。",
      "source": "环球市场播报",
      "category": "a-stock"
    },
    {
      "title": "Replenish Nutrients获SRC 1500万加元战略投资，自有产能将提升五倍",
      "link": "https://finance.sina.com.cn/stock/usstock/c/2026-07-21/doc-iniinwmu8208240.shtml",
      "date": "2026-07-21 03:36",
      "summary": "再生农业肥料公司Replenish Nutrients Holding Corp．周一宣布，已与SRC Agrominerals达成一项1500万加元的战略投资协议。该投资将用于在艾伯塔省Beiseker现有厂区新建一座...",
      "source": "环球市场播报",
      "category": "a-stock"
    }
  ]
}