{
  "updated": "2026-07-24T21:28:55.421493+08:00",
  "source": "个股公告",
  "count": 29,
  "items": [
    {
      "title": "ST葫芦娃:海南葫芦娃药业集团股份有限公司关于为全资子公司提供担保的公告",
      "link": "https://data.eastmoney.com/notices/detail/605199/20260725/AN202607241827328005.html",
      "date": "2026-07-24 21:28",
      "summary": "",
      "source": "公告API",
      "category": "announce",
      "stock_code": "605199",
      "stock_name": "ST葫芦娃"
    },
    {
      "title": "滨化股份:滨化股份关于股票交易风险的提示性公告",
      "link": "https://data.eastmoney.com/notices/detail/601678/20260725/AN202607241827326871.html",
      "date": "2026-07-24 21:28",
      "summary": "",
      "source": "公告API",
      "category": "announce",
      "stock_code": "601678",
      "stock_name": "滨化股份"
    },
    {
      "title": "*ST宝馨:关于调整公司第六届董事会专门委员会委员的公告",
      "link": "https://data.eastmoney.com/notices/detail/002514/20260725/AN202607241827326825.html",
      "date": "2026-07-24 21:28",
      "summary": "",
      "source": "公告API",
      "category": "announce",
      "stock_code": "002514",
      "stock_name": "*ST宝馨"
    },
    {
      "title": "*ST宝馨:关于独立董事取得独立董事资格证书的公告",
      "link": "https://data.eastmoney.com/notices/detail/002514/20260725/AN202607241827326827.html",
      "date": "2026-07-24 21:28",
      "summary": "",
      "source": "公告API",
      "category": "announce",
      "stock_code": "002514",
      "stock_name": "*ST宝馨"
    },
    {
      "title": "*ST宝馨:第六届董事会第三十次会议决议公告",
      "link": "https://data.eastmoney.com/notices/detail/002514/20260725/AN202607241827326829.html",
      "date": "2026-07-24 21:28",
      "summary": "",
      "source": "公告API",
      "category": "announce",
      "stock_code": "002514",
      "stock_name": "*ST宝馨"
    },
    {
      "title": "*ST宝馨:关于变更财务总监的公告",
      "link": "https://data.eastmoney.com/notices/detail/002514/20260725/AN202607241827326828.html",
      "date": "2026-07-24 21:28",
      "summary": "",
      "source": "公告API",
      "category": "announce",
      "stock_code": "002514",
      "stock_name": "*ST宝馨"
    },
    {
      "title": "*ST宝馨:关于董事会秘书辞职的公告",
      "link": "https://data.eastmoney.com/notices/detail/002514/20260725/AN202607241827326826.html",
      "date": "2026-07-24 21:28",
      "summary": "",
      "source": "公告API",
      "category": "announce",
      "stock_code": "002514",
      "stock_name": "*ST宝馨"
    },
    {
      "title": "皮阿诺:关于与特定对象签署《附条件生效的股份认购协议》暨关联交易的公告",
      "link": "https://data.eastmoney.com/notices/detail/002853/20260725/AN202607241827326823.html",
      "date": "2026-07-24 21:28",
      "summary": "",
      "source": "公告API",
      "category": "announce",
      "stock_code": "002853",
      "stock_name": "皮阿诺"
    },
    {
      "title": "皮阿诺:关于本次向特定对象发行A股股票不存在直接或通过利益相关方向参与认购的投资者提供财务资助或补偿的公告",
      "link": "https://data.eastmoney.com/notices/detail/002853/20260725/AN202607241827326813.html",
      "date": "2026-07-24 21:28",
      "summary": "",
      "source": "公告API",
      "category": "announce",
      "stock_code": "002853",
      "stock_name": "皮阿诺"
    },
    {
      "title": "皮阿诺:关于控股股东上层股权结构发生变动的提示性公告",
      "link": "https://data.eastmoney.com/notices/detail/002853/20260725/AN202607241827326816.html",
      "date": "2026-07-24 21:28",
      "summary": "",
      "source": "公告API",
      "category": "announce",
      "stock_code": "002853",
      "stock_name": "皮阿诺"
    },
    {
      "title": "皮阿诺:关于向特定对象发行A股股票导致股东权益变动的提示性公告",
      "link": "https://data.eastmoney.com/notices/detail/002853/20260725/AN202607241827326818.html",
      "date": "2026-07-24 21:28",
      "summary": "",
      "source": "公告API",
      "category": "announce",
      "stock_code": "002853",
      "stock_name": "皮阿诺"
    },
    {
      "title": "*ST岭南:关于公司股票存在可能因股价低于面值被终止上市的风险提示公告",
      "link": "https://data.eastmoney.com/notices/detail/002717/20260725/AN202607241827326806.html",
      "date": "2026-07-24 21:28",
      "summary": "",
      "source": "公告API",
      "category": "announce",
      "stock_code": "002717",
      "stock_name": "*ST岭南"
    },
    {
      "title": "皮阿诺:国信证券股份有限公司关于广东皮阿诺科学艺术家居股份有限公司详式权益变动报告书之财务顾问核查意见(修订稿)",
      "link": "https://data.eastmoney.com/notices/detail/002853/20260725/AN202607241827326805.html",
      "date": "2026-07-24 21:28",
      "summary": "",
      "source": "公告API",
      "category": "announce",
      "stock_code": "002853",
      "stock_name": "皮阿诺"
    },
    {
      "title": "皮阿诺:公司2025年度向特定对象发行A股股票募集资金使用可行性分析报告(修订稿)",
      "link": "https://data.eastmoney.com/notices/detail/002853/20260725/AN202607241827326807.html",
      "date": "2026-07-24 21:28",
      "summary": "",
      "source": "公告API",
      "category": "announce",
      "stock_code": "002853",
      "stock_name": "皮阿诺"
    },
    {
      "title": "皮阿诺:未来三年(2026-2028年)股东分红回报规划",
      "link": "https://data.eastmoney.com/notices/detail/002853/20260725/AN202607241827326824.html",
      "date": "2026-07-24 21:28",
      "summary": "",
      "source": "公告API",
      "category": "announce",
      "stock_code": "002853",
      "stock_name": "皮阿诺"
    },
    {
      "title": "*ST岭南:关于岭南转债第四期偿付安排的公告",
      "link": "https://data.eastmoney.com/notices/detail/002717/20260725/AN202607241827326801.html",
      "date": "2026-07-24 21:28",
      "summary": "",
      "source": "公告API",
      "category": "announce",
      "stock_code": "002717",
      "stock_name": "*ST岭南"
    },
    {
      "title": "皮阿诺:关于召开公司2026年第五次临时股东会的通知",
      "link": "https://data.eastmoney.com/notices/detail/002853/20260725/AN202607241827326821.html",
      "date": "2026-07-24 21:28",
      "summary": "",
      "source": "公告API",
      "category": "announce",
      "stock_code": "002853",
      "stock_name": "皮阿诺"
    },
    {
      "title": "皮阿诺:关于调整公司2025年度向特定对象发行A股股票方案的公告",
      "link": "https://data.eastmoney.com/notices/detail/002853/20260725/AN202607241827326822.html",
      "date": "2026-07-24 21:28",
      "summary": "",
      "source": "公告API",
      "category": "announce",
      "stock_code": "002853",
      "stock_name": "皮阿诺"
    },
    {
      "title": "皮阿诺:关于2025年度向特定对象发行A股股票预案(修订稿)披露的提示性公告",
      "link": "https://data.eastmoney.com/notices/detail/002853/20260725/AN202607241827326817.html",
      "date": "2026-07-24 21:28",
      "summary": "",
      "source": "公告API",
      "category": "announce",
      "stock_code": "002853",
      "stock_name": "皮阿诺"
    },
    {
      "title": "皮阿诺:公司2025年度向特定对象发行A股股票预案(修订稿)",
      "link": "https://data.eastmoney.com/notices/detail/002853/20260725/AN202607241827326809.html",
      "date": "2026-07-24 21:28",
      "summary": "",
      "source": "公告API",
      "category": "announce",
      "stock_code": "002853",
      "stock_name": "皮阿诺"
    },
    {
      "title": "皮阿诺:关于2025年度向特定对象发行A股股票摊薄即期回报及采取填补措施、相关主体承诺(修订稿)的公告",
      "link": "https://data.eastmoney.com/notices/detail/002853/20260725/AN202607241827326802.html",
      "date": "2026-07-24 21:28",
      "summary": "",
      "source": "公告API",
      "category": "announce",
      "stock_code": "002853",
      "stock_name": "皮阿诺"
    },
    {
      "title": "皮阿诺:关于2025年度向特定对象发行A股股票方案的论证分析报告(修订稿)",
      "link": "https://data.eastmoney.com/notices/detail/002853/20260725/AN202607241827326820.html",
      "date": "2026-07-24 21:28",
      "summary": "",
      "source": "公告API",
      "category": "announce",
      "stock_code": "002853",
      "stock_name": "皮阿诺"
    },
    {
      "title": "皮阿诺:详式权益变动报告书(修订稿)",
      "link": "https://data.eastmoney.com/notices/detail/002853/20260725/AN202607241827326812.html",
      "date": "2026-07-24 21:28",
      "summary": "",
      "source": "公告API",
      "category": "announce",
      "stock_code": "002853",
      "stock_name": "皮阿诺"
    },
    {
      "title": "皮阿诺:第五届董事会第四次会议决议公告",
      "link": "https://data.eastmoney.com/notices/detail/002853/20260725/AN202607241827326810.html",
      "date": "2026-07-24 21:28",
      "summary": "",
      "source": "公告API",
      "category": "announce",
      "stock_code": "002853",
      "stock_name": "皮阿诺"
    },
    {
      "title": "皮阿诺:关于签署《附条件生效的股份认购协议之终止协议》暨关联交易的公告",
      "link": "https://data.eastmoney.com/notices/detail/002853/20260725/AN202607241827326808.html",
      "date": "2026-07-24 21:28",
      "summary": "",
      "source": "公告API",
      "category": "announce",
      "stock_code": "002853",
      "stock_name": "皮阿诺"
    },
    {
      "title": "*ST岭南:关于股东部分股份将被司法拍卖的公告",
      "link": "https://data.eastmoney.com/notices/detail/002717/20260725/AN202607241827326815.html",
      "date": "2026-07-24 21:28",
      "summary": "",
      "source": "公告API",
      "category": "announce",
      "stock_code": "002717",
      "stock_name": "*ST岭南"
    },
    {
      "title": "嘉美包装:会计师事务所选聘制度(2026年7月)",
      "link": "https://data.eastmoney.com/notices/detail/002969/20260725/AN202607241827326772.html",
      "date": "2026-07-24 21:28",
      "summary": "",
      "source": "公告API",
      "category": "announce",
      "stock_code": "002969",
      "stock_name": "嘉美包装"
    },
    {
      "title": "嘉美包装:关于调整公司组织架构的公告",
      "link": "https://data.eastmoney.com/notices/detail/002969/20260725/AN202607241827326736.html",
      "date": "2026-07-24 21:28",
      "summary": "",
      "source": "公告API",
      "category": "announce",
      "stock_code": "002969",
      "stock_name": "嘉美包装"
    },
    {
      "title": "嘉美包装:股东会议事规则(2026年7月修订)",
      "link": "https://data.eastmoney.com/notices/detail/002969/20260725/AN202607241827326765.html",
      "date": "2026-07-24 21:28",
      "summary": "",
      "source": "公告API",
      "category": "announce",
      "stock_code": "002969",
      "stock_name": "嘉美包装"
    }
  ]
}