{
  "updated": "2026-07-07T18:06:10.144612+08:00",
  "source": "个股公告",
  "count": 29,
  "items": [
    {
      "title": "贝肯能源:关于控股股东、实际控制人及其原一致行动人股份减持计划实施完成暨内部转让股份的公告",
      "link": "https://data.eastmoney.com/notices/detail/002828/20260708/AN202607071826775697.html",
      "date": "2026-07-07 18:06",
      "summary": "",
      "source": "公告API",
      "category": "announce",
      "stock_code": "002828",
      "stock_name": "贝肯能源"
    },
    {
      "title": "*ST准油:关于公司办公地址及联系信息变更的公告",
      "link": "https://data.eastmoney.com/notices/detail/002207/20260708/AN202607071826775695.html",
      "date": "2026-07-07 18:06",
      "summary": "",
      "source": "公告API",
      "category": "announce",
      "stock_code": "002207",
      "stock_name": "*ST准油"
    },
    {
      "title": "百润股份:2026年第二次临时股东会决议公告",
      "link": "https://data.eastmoney.com/notices/detail/002568/20260708/AN202607071826775696.html",
      "date": "2026-07-07 18:06",
      "summary": "",
      "source": "公告API",
      "category": "announce",
      "stock_code": "002568",
      "stock_name": "百润股份"
    },
    {
      "title": "金安国纪:关于独立董事减持股份实施情况公告",
      "link": "https://data.eastmoney.com/notices/detail/002636/20260708/AN202607071826775659.html",
      "date": "2026-07-07 18:06",
      "summary": "",
      "source": "公告API",
      "category": "announce",
      "stock_code": "002636",
      "stock_name": "金安国纪"
    },
    {
      "title": "宗申动力:关于持股5%以上股东股份减持计划期限届满未实施减持的公告",
      "link": "https://data.eastmoney.com/notices/detail/001696/20260708/AN202607071826775601.html",
      "date": "2026-07-07 18:06",
      "summary": "",
      "source": "公告API",
      "category": "announce",
      "stock_code": "001696",
      "stock_name": "宗申动力"
    },
    {
      "title": "汇绿生态:关于部分限制性股票回购注销完成的公告",
      "link": "https://data.eastmoney.com/notices/detail/001267/20260708/AN202607071826775600.html",
      "date": "2026-07-07 18:06",
      "summary": "",
      "source": "公告API",
      "category": "announce",
      "stock_code": "001267",
      "stock_name": "汇绿生态"
    },
    {
      "title": "百润股份:上海市锦天城律师事务所关于上海百润投资控股集团股份有限公司2026年第二次临时股东会法律意见书",
      "link": "https://data.eastmoney.com/notices/detail/002568/20260708/AN202607071826775598.html",
      "date": "2026-07-07 18:06",
      "summary": "",
      "source": "公告API",
      "category": "announce",
      "stock_code": "002568",
      "stock_name": "百润股份"
    },
    {
      "title": "天齐锂业:关于债务融资工具获准注册的公告",
      "link": "https://data.eastmoney.com/notices/detail/002466/20260708/AN202607071826775492.html",
      "date": "2026-07-07 18:06",
      "summary": "",
      "source": "公告API",
      "category": "announce",
      "stock_code": "002466",
      "stock_name": "天齐锂业"
    },
    {
      "title": "思看科技:中信证券股份有限公司关于思看科技(杭州)股份有限公司开展外汇衍生品交易业务的核查意见",
      "link": "https://data.eastmoney.com/notices/detail/688583/20260708/AN202607071826775478.html",
      "date": "2026-07-07 18:06",
      "summary": "",
      "source": "公告API",
      "category": "announce",
      "stock_code": "688583",
      "stock_name": "思看科技"
    },
    {
      "title": "思看科技:关于开展外汇衍生品交易的公告",
      "link": "https://data.eastmoney.com/notices/detail/688583/20260708/AN202607071826775479.html",
      "date": "2026-07-07 18:06",
      "summary": "",
      "source": "公告API",
      "category": "announce",
      "stock_code": "688583",
      "stock_name": "思看科技"
    },
    {
      "title": "统联精密:董事会薪酬与考核委员会关于公司2024年限制性股票激励计划第二个归属期归属名单的核查意见",
      "link": "https://data.eastmoney.com/notices/detail/688210/20260708/AN202607071826775447.html",
      "date": "2026-07-07 18:06",
      "summary": "",
      "source": "公告API",
      "category": "announce",
      "stock_code": "688210",
      "stock_name": "统联精密"
    },
    {
      "title": "统联精密:关于部分募投项目结项并将节余募集资金永久补充流动资金的公告",
      "link": "https://data.eastmoney.com/notices/detail/118066/20260708/AN202607071826775451.html",
      "date": "2026-07-07 18:06",
      "summary": "",
      "source": "公告API",
      "category": "announce",
      "stock_code": "118066",
      "stock_name": "统联转债"
    },
    {
      "title": "统联精密:国金证券股份有限公司关于深圳市泛海统联精密制造股份有限公司与私募基金合作投资暨关联交易的核查意见",
      "link": "https://data.eastmoney.com/notices/detail/688210/20260708/AN202607071826775452.html",
      "date": "2026-07-07 18:06",
      "summary": "",
      "source": "公告API",
      "category": "announce",
      "stock_code": "688210",
      "stock_name": "统联精密"
    },
    {
      "title": "统联精密:关于作废部分已授予尚未归属的2024年限制性股票的公告",
      "link": "https://data.eastmoney.com/notices/detail/118066/20260708/AN202607071826775448.html",
      "date": "2026-07-07 18:06",
      "summary": "",
      "source": "公告API",
      "category": "announce",
      "stock_code": "118066",
      "stock_name": "统联转债"
    },
    {
      "title": "统联精密:上海君澜律师事务所关于深圳市泛海统联精密制造股份有限公司2024年限制性股票激励计划作废及归属相关事项之法律意见书",
      "link": "https://data.eastmoney.com/notices/detail/688210/20260708/AN202607071826775449.html",
      "date": "2026-07-07 18:06",
      "summary": "",
      "source": "公告API",
      "category": "announce",
      "stock_code": "688210",
      "stock_name": "统联精密"
    },
    {
      "title": "统联精密:关于2024年限制性股票激励计划第二个归属期归属条件成就的公告",
      "link": "https://data.eastmoney.com/notices/detail/118066/20260708/AN202607071826775453.html",
      "date": "2026-07-07 18:06",
      "summary": "",
      "source": "公告API",
      "category": "announce",
      "stock_code": "118066",
      "stock_name": "统联转债"
    },
    {
      "title": "统联精密:关于第三届董事会第二次会议决议的公告",
      "link": "https://data.eastmoney.com/notices/detail/118066/20260708/AN202607071826775454.html",
      "date": "2026-07-07 18:06",
      "summary": "",
      "source": "公告API",
      "category": "announce",
      "stock_code": "118066",
      "stock_name": "统联转债"
    },
    {
      "title": "统联精密:关于与私募基金合作投资暨关联交易的公告",
      "link": "https://data.eastmoney.com/notices/detail/118066/20260708/AN202607071826775444.html",
      "date": "2026-07-07 18:06",
      "summary": "",
      "source": "公告API",
      "category": "announce",
      "stock_code": "118066",
      "stock_name": "统联转债"
    },
    {
      "title": "大晟文化:关于召开2025年度及2026年第一季度业绩说明会的公告",
      "link": "https://data.eastmoney.com/notices/detail/600892/20260708/AN202607071826775398.html",
      "date": "2026-07-07 18:06",
      "summary": "",
      "source": "公告API",
      "category": "announce",
      "stock_code": "600892",
      "stock_name": "大晟文化"
    },
    {
      "title": "东瑞股份:2026年6月份生猪销售简报",
      "link": "https://data.eastmoney.com/notices/detail/001201/20260708/AN202607071826775402.html",
      "date": "2026-07-07 18:06",
      "summary": "",
      "source": "公告API",
      "category": "announce",
      "stock_code": "001201",
      "stock_name": "东瑞股份"
    },
    {
      "title": "欧普照明:上海市通力律师事务所关于欧普照明股份有限公司2023年、2024年限制性股票激励计划部分限制性股票回购注销实施的法律意见书",
      "link": "https://data.eastmoney.com/notices/detail/603515/20260708/AN202607071826775361.html",
      "date": "2026-07-07 18:06",
      "summary": "",
      "source": "公告API",
      "category": "announce",
      "stock_code": "603515",
      "stock_name": "欧普照明"
    },
    {
      "title": "欧普照明:欧普照明股份有限公司股权激励限制性股票回购注销实施公告",
      "link": "https://data.eastmoney.com/notices/detail/603515/20260708/AN202607071826775359.html",
      "date": "2026-07-07 18:06",
      "summary": "",
      "source": "公告API",
      "category": "announce",
      "stock_code": "603515",
      "stock_name": "欧普照明"
    },
    {
      "title": "柏诚股份:关于回购注销部分限制性股票暨通知债权人的公告",
      "link": "https://data.eastmoney.com/notices/detail/601133/20260708/AN202607071826775342.html",
      "date": "2026-07-07 18:06",
      "summary": "",
      "source": "公告API",
      "category": "announce",
      "stock_code": "601133",
      "stock_name": "柏诚股份"
    },
    {
      "title": "柏诚股份:关于调整2024年限制性股票激励计划回购价格及回购注销部分限制性股票的公告",
      "link": "https://data.eastmoney.com/notices/detail/601133/20260708/AN202607071826775338.html",
      "date": "2026-07-07 18:06",
      "summary": "",
      "source": "公告API",
      "category": "announce",
      "stock_code": "601133",
      "stock_name": "柏诚股份"
    },
    {
      "title": "柏诚股份:关于召开2026年第二次临时股东会的通知",
      "link": "https://data.eastmoney.com/notices/detail/601133/20260708/AN202607071826775333.html",
      "date": "2026-07-07 18:06",
      "summary": "",
      "source": "公告API",
      "category": "announce",
      "stock_code": "601133",
      "stock_name": "柏诚股份"
    },
    {
      "title": "柏诚股份:国浩律师(南京)事务所关于柏诚系统科技股份有限公司2024年限制性股票激励计划回购注销部分已授予限制性股票的法律意见书",
      "link": "https://data.eastmoney.com/notices/detail/601133/20260708/AN202607071826775337.html",
      "date": "2026-07-07 18:06",
      "summary": "",
      "source": "公告API",
      "category": "announce",
      "stock_code": "601133",
      "stock_name": "柏诚股份"
    },
    {
      "title": "柏诚股份:关于开展外汇套期保值业务的可行性分析报告",
      "link": "https://data.eastmoney.com/notices/detail/601133/20260708/AN202607071826775332.html",
      "date": "2026-07-07 18:06",
      "summary": "",
      "source": "公告API",
      "category": "announce",
      "stock_code": "601133",
      "stock_name": "柏诚股份"
    },
    {
      "title": "柏诚股份:关于开展外汇套期保值业务的公告",
      "link": "https://data.eastmoney.com/notices/detail/601133/20260708/AN202607071826775340.html",
      "date": "2026-07-07 18:06",
      "summary": "",
      "source": "公告API",
      "category": "announce",
      "stock_code": "601133",
      "stock_name": "柏诚股份"
    },
    {
      "title": "柏诚股份:柏诚系统科技股份有限公司章程(2026年7月修订)",
      "link": "https://data.eastmoney.com/notices/detail/601133/20260708/AN202607071826775336.html",
      "date": "2026-07-07 18:06",
      "summary": "",
      "source": "公告API",
      "category": "announce",
      "stock_code": "601133",
      "stock_name": "柏诚股份"
    }
  ]
}