{
  "updated": "2026-06-30T18:56:56.714510+08:00",
  "source": "个股公告",
  "count": 30,
  "items": [
    {
      "title": "ST晨鸣:2026年第一次临时股东会决议公告",
      "link": "https://data.eastmoney.com/notices/detail/000488/20260701/AN202606301826599921.html",
      "date": "2026-06-30 18:56",
      "summary": "",
      "source": "公告API",
      "category": "announce",
      "stock_code": "000488",
      "stock_name": "ST晨鸣"
    },
    {
      "title": "ST晨鸣:北京市中伦(青岛)律师事务所关于山东晨鸣纸业集团股份有限公司2026年第一次临时股东会之法律意见书",
      "link": "https://data.eastmoney.com/notices/detail/000488/20260701/AN202606301826599924.html",
      "date": "2026-06-30 18:56",
      "summary": "",
      "source": "公告API",
      "category": "announce",
      "stock_code": "000488",
      "stock_name": "ST晨鸣"
    },
    {
      "title": "兴业科技:兴业皮革科技股份有限公司关于控股股东股份质押的公告",
      "link": "https://data.eastmoney.com/notices/detail/002674/20260701/AN202606301826599928.html",
      "date": "2026-06-30 18:56",
      "summary": "",
      "source": "公告API",
      "category": "announce",
      "stock_code": "002674",
      "stock_name": "兴业科技"
    },
    {
      "title": "乐通股份:2026年第二次临时股东会法律意见书",
      "link": "https://data.eastmoney.com/notices/detail/002319/20260701/AN202606301826599940.html",
      "date": "2026-06-30 18:56",
      "summary": "",
      "source": "公告API",
      "category": "announce",
      "stock_code": "002319",
      "stock_name": "乐通股份"
    },
    {
      "title": "万科A:关于在交易商协会披露《关于2023年度第四期中期票据本息偿付安排的公告》的提示性公告",
      "link": "https://data.eastmoney.com/notices/detail/000002/20260701/AN202606301826599925.html",
      "date": "2026-06-30 18:56",
      "summary": "",
      "source": "公告API",
      "category": "announce",
      "stock_code": "000002",
      "stock_name": "万科A"
    },
    {
      "title": "电投绿能:关于退出并清算吉电清能工融(北京)股权投资基金合伙企业(有限合伙)暨关联交易的进展公告",
      "link": "https://data.eastmoney.com/notices/detail/000875/20260701/AN202606301826599919.html",
      "date": "2026-06-30 18:56",
      "summary": "",
      "source": "公告API",
      "category": "announce",
      "stock_code": "000875",
      "stock_name": "电投绿能"
    },
    {
      "title": "柳工:关于回购股份并注销的公告",
      "link": "https://data.eastmoney.com/notices/detail/000528/20260701/AN202606301826599932.html",
      "date": "2026-06-30 18:56",
      "summary": "",
      "source": "公告API",
      "category": "announce",
      "stock_code": "000528",
      "stock_name": "柳工"
    },
    {
      "title": "乐通股份:关于《债权债务确认及还款协议之二》到期暨关联交易的进展公告",
      "link": "https://data.eastmoney.com/notices/detail/002319/20260701/AN202606301826599927.html",
      "date": "2026-06-30 18:56",
      "summary": "",
      "source": "公告API",
      "category": "announce",
      "stock_code": "002319",
      "stock_name": "乐通股份"
    },
    {
      "title": "华宏科技:关于公司控股股东、部分董事及高级管理人员减持股份预披露公告",
      "link": "https://data.eastmoney.com/notices/detail/002645/20260701/AN202606301826599935.html",
      "date": "2026-06-30 18:56",
      "summary": "",
      "source": "公告API",
      "category": "announce",
      "stock_code": "002645",
      "stock_name": "华宏科技"
    },
    {
      "title": "柳工:关于召开2026年第三次临时股东会的通知",
      "link": "https://data.eastmoney.com/notices/detail/000528/20260701/AN202606301826599934.html",
      "date": "2026-06-30 18:56",
      "summary": "",
      "source": "公告API",
      "category": "announce",
      "stock_code": "000528",
      "stock_name": "柳工"
    },
    {
      "title": "电投绿能:关于吉远(四平)绿色能源有限公司拟采购上海能源科技发展有限公司30万千瓦风电PC施工总承包服务关联交易的公告",
      "link": "https://data.eastmoney.com/notices/detail/000875/20260701/AN202606301826599923.html",
      "date": "2026-06-30 18:56",
      "summary": "",
      "source": "公告API",
      "category": "announce",
      "stock_code": "000875",
      "stock_name": "电投绿能"
    },
    {
      "title": "万科A:关于独立董事任期届满辞任的公告",
      "link": "https://data.eastmoney.com/notices/detail/000002/20260701/AN202606301826599920.html",
      "date": "2026-06-30 18:56",
      "summary": "",
      "source": "公告API",
      "category": "announce",
      "stock_code": "000002",
      "stock_name": "万科A"
    },
    {
      "title": "柳工:第十届董事会第十四次(临时)会议决议公告",
      "link": "https://data.eastmoney.com/notices/detail/000528/20260701/AN202606301826599936.html",
      "date": "2026-06-30 18:56",
      "summary": "",
      "source": "公告API",
      "category": "announce",
      "stock_code": "000528",
      "stock_name": "柳工"
    },
    {
      "title": "乐通股份:2026年第二次临时股东会会议决议公告",
      "link": "https://data.eastmoney.com/notices/detail/002319/20260701/AN202606301826599931.html",
      "date": "2026-06-30 18:56",
      "summary": "",
      "source": "公告API",
      "category": "announce",
      "stock_code": "002319",
      "stock_name": "乐通股份"
    },
    {
      "title": "电投绿能:第十届董事会第十一次会议决议公告",
      "link": "https://data.eastmoney.com/notices/detail/000875/20260701/AN202606301826599922.html",
      "date": "2026-06-30 18:56",
      "summary": "",
      "source": "公告API",
      "category": "announce",
      "stock_code": "000875",
      "stock_name": "电投绿能"
    },
    {
      "title": "电投绿能:关于召开2026年第三次临时股东会的通知",
      "link": "https://data.eastmoney.com/notices/detail/000875/20260701/AN202606301826599939.html",
      "date": "2026-06-30 18:56",
      "summary": "",
      "source": "公告API",
      "category": "announce",
      "stock_code": "000875",
      "stock_name": "电投绿能"
    },
    {
      "title": "电投绿能:关于申请注册发行公司债券的公告",
      "link": "https://data.eastmoney.com/notices/detail/000875/20260701/AN202606301826599938.html",
      "date": "2026-06-30 18:56",
      "summary": "",
      "source": "公告API",
      "category": "announce",
      "stock_code": "000875",
      "stock_name": "电投绿能"
    },
    {
      "title": "电投绿能:关于调整投资建设山东潍坊风光储多能互补试点首批四期450兆瓦光伏(储能)项目暨进展公告",
      "link": "https://data.eastmoney.com/notices/detail/000875/20260701/AN202606301826599937.html",
      "date": "2026-06-30 18:56",
      "summary": "",
      "source": "公告API",
      "category": "announce",
      "stock_code": "000875",
      "stock_name": "电投绿能"
    },
    {
      "title": "柳工:关于修订《公司章程》的公告",
      "link": "https://data.eastmoney.com/notices/detail/000528/20260701/AN202606301826599933.html",
      "date": "2026-06-30 18:56",
      "summary": "",
      "source": "公告API",
      "category": "announce",
      "stock_code": "000528",
      "stock_name": "柳工"
    },
    {
      "title": "万科A:关于担保进展情况的公告",
      "link": "https://data.eastmoney.com/notices/detail/000002/20260701/AN202606301826599930.html",
      "date": "2026-06-30 18:56",
      "summary": "",
      "source": "公告API",
      "category": "announce",
      "stock_code": "000002",
      "stock_name": "万科A"
    },
    {
      "title": "柳工:关于公司调整财务负责人暨新聘副总裁的公告",
      "link": "https://data.eastmoney.com/notices/detail/000528/20260701/AN202606301826599929.html",
      "date": "2026-06-30 18:56",
      "summary": "",
      "source": "公告API",
      "category": "announce",
      "stock_code": "000528",
      "stock_name": "柳工"
    },
    {
      "title": "华林证券:关于控股股东部分股份解除质押及再质押的公告",
      "link": "https://data.eastmoney.com/notices/detail/002945/20260701/AN202606301826599926.html",
      "date": "2026-06-30 18:56",
      "summary": "",
      "source": "公告API",
      "category": "announce",
      "stock_code": "002945",
      "stock_name": "华林证券"
    },
    {
      "title": "德马科技:德马科技关于2025年年度报告的信息披露监管问询函的回复公告",
      "link": "https://data.eastmoney.com/notices/detail/688360/20260701/AN202606301826599910.html",
      "date": "2026-06-30 18:56",
      "summary": "",
      "source": "公告API",
      "category": "announce",
      "stock_code": "688360",
      "stock_name": "德马科技"
    },
    {
      "title": "德马科技:国金证券股份有限公司关于对德马科技集团股份有限公司2025年年度报告的信息披露监管问询函的回复",
      "link": "https://data.eastmoney.com/notices/detail/688360/20260701/AN202606301826599909.html",
      "date": "2026-06-30 18:56",
      "summary": "",
      "source": "公告API",
      "category": "announce",
      "stock_code": "688360",
      "stock_name": "德马科技"
    },
    {
      "title": "ST信通:亿阳信通关于公司董事会换届完成的公告",
      "link": "https://data.eastmoney.com/notices/detail/600289/20260701/AN202606301826599816.html",
      "date": "2026-06-30 18:56",
      "summary": "",
      "source": "公告API",
      "category": "announce",
      "stock_code": "600289",
      "stock_name": "ST信通"
    },
    {
      "title": "ST信通:亿阳信通2025年年度股东会法律意见书",
      "link": "https://data.eastmoney.com/notices/detail/600289/20260701/AN202606301826599812.html",
      "date": "2026-06-30 18:56",
      "summary": "",
      "source": "公告API",
      "category": "announce",
      "stock_code": "600289",
      "stock_name": "ST信通"
    },
    {
      "title": "ST信通:亿阳信通关于涉及投资者诉讼事项进展的公告",
      "link": "https://data.eastmoney.com/notices/detail/600289/20260701/AN202606301826599817.html",
      "date": "2026-06-30 18:56",
      "summary": "",
      "source": "公告API",
      "category": "announce",
      "stock_code": "600289",
      "stock_name": "ST信通"
    },
    {
      "title": "ST信通:亿阳信通关于第十届董事会第一次会议决议的公告",
      "link": "https://data.eastmoney.com/notices/detail/600289/20260701/AN202606301826599814.html",
      "date": "2026-06-30 18:56",
      "summary": "",
      "source": "公告API",
      "category": "announce",
      "stock_code": "600289",
      "stock_name": "ST信通"
    },
    {
      "title": "ST信通:亿阳信通2025年年度股东会决议公告",
      "link": "https://data.eastmoney.com/notices/detail/600289/20260701/AN202606301826599813.html",
      "date": "2026-06-30 18:56",
      "summary": "",
      "source": "公告API",
      "category": "announce",
      "stock_code": "600289",
      "stock_name": "ST信通"
    },
    {
      "title": "中青旅:中青旅2026年第一次临时股东会决议公告",
      "link": "https://data.eastmoney.com/notices/detail/600138/20260701/AN202606301826599797.html",
      "date": "2026-06-30 18:56",
      "summary": "",
      "source": "公告API",
      "category": "announce",
      "stock_code": "600138",
      "stock_name": "中青旅"
    }
  ]
}